deep_toggl/__init__.py
deep_toggl/__main__.py
deep_toggl/cli.py
deep_toggl/config.py
deep_toggl/evaluator.py
deep_toggl/summarizer.py
deep_toggl-0.5.dist-info/METADATA
deep_toggl-0.5.dist-info/WHEEL
deep_toggl-0.5.dist-info/entry_points.txt
deep_toggl-0.5.dist-info/top_level.txt
deep_toggl-0.5.dist-info/RECORD
